sag_py_logging/__init__.py
sag_py_logging/console_extra_field_filter.py
sag_py_logging/log_config_initializer.py
sag_py_logging/log_config_loader.py
sag_py_logging/log_config_processors.py
sag_py_logging/models.py
sag_py_logging/py.typed
sag_py_logging-0.4.2.dist-info/licenses/LICENSE.txt
sag_py_logging-0.4.2.dist-info/METADATA
sag_py_logging-0.4.2.dist-info/WHEEL
sag_py_logging-0.4.2.dist-info/top_level.txt
sag_py_logging-0.4.2.dist-info/RECORD
