Metadata-Version: 2.4
Name: sag-py-logging
Version: 0.4.2
Summary: Initialize logging from a configuration json
Home-page: https://github.com/SamhammerAG/sag_py_logging
Author: Samhammer AG
Author-email: support@samhammer.de
License: MIT
Project-URL: Documentation, https://github.com/SamhammerAG/sag_py_logging
Project-URL: Bug Reports, https://github.com/SamhammerAG/sag_py_logging/issues
Project-URL: Source, https://github.com/SamhammerAG/sag_py_logging
Keywords: logging,extra,fields
Classifier: Programming Language :: Python :: 3
Classifier: License :: OSI Approved :: MIT License
Classifier: Operating System :: OS Independent
Classifier: Topic :: Software Development :: Libraries :: Python Modules
Classifier: Topic :: Software Development :: Libraries
Classifier: Topic :: Software Development
Requires-Python: >=3.12
License-File: LICENSE.txt
Provides-Extra: dev
Requires-Dist: build; extra == "dev"
Requires-Dist: flake8; extra == "dev"
Requires-Dist: mypy; extra == "dev"
Requires-Dist: pytest; extra == "dev"
Requires-Dist: pytest-asyncio; extra == "dev"
Requires-Dist: pytest-cov; extra == "dev"
Requires-Dist: coverage; extra == "dev"
Requires-Dist: coverage-lcov; extra == "dev"
Requires-Dist: toml; extra == "dev"
Requires-Dist: attrs; extra == "dev"
Requires-Dist: mock; extra == "dev"
Requires-Dist: types-mock; extra == "dev"
Requires-Dist: Jinja2>=3.1.6; extra == "dev"
Requires-Dist: tomli>=2.2.1; extra == "dev"
Requires-Dist: zipp>=3.21.0; extra == "dev"
Provides-Extra: jinja
Requires-Dist: Jinja2>=3.1.6; extra == "jinja"
Provides-Extra: toml
Requires-Dist: tomli>=2.2.1; extra == "toml"
Dynamic: author
Dynamic: author-email
Dynamic: classifier
Dynamic: description
Dynamic: description-content-type
Dynamic: home-page
Dynamic: keywords
Dynamic: license
Dynamic: license-file
Dynamic: project-url
Dynamic: provides-extra
Dynamic: requires-python
Dynamic: summary
